pylp/__init__.py
pylp/__main__.py
pylp/cli/__init__.py
pylp/cli/cli.py
pylp/cli/colors.py
pylp/cli/logger.py
pylp/cli/run.py
pylp/lib/__init__.py
pylp/lib/config.py
pylp/lib/dest.py
pylp/lib/file.py
pylp/lib/runner.py
pylp/lib/src.py
pylp/lib/stream.py
pylp/lib/tasks.py
pylp/lib/transformer.py
pylp/utils/__init__.py
pylp/utils/decorators.py
pylp/utils/glob.py
pylp/utils/paths.py
pylp/utils/pipes.py
pylp/utils/time.py
pylp-0.2.10.dist-info/DESCRIPTION.rst
pylp-0.2.10.dist-info/METADATA
pylp-0.2.10.dist-info/RECORD
pylp-0.2.10.dist-info/WHEEL
pylp-0.2.10.dist-info/entry_points.txt
pylp-0.2.10.dist-info/metadata.json
pylp-0.2.10.dist-info/top_level.txt
