Metadata-Version: 2.0
Name: pylp
Version: 0.2.10
Summary: A Python task runner inspired by gulp.js
Home-page: https://github.com/pylp/pylp
Author: Guillaume Gonnet
Author-email: gonnet.guillaume97@gmail.com
License: MIT
Keywords: pylp build task runner gulp
Platform: UNKNOWN
Classifier: Development Status :: 4 - Beta
Classifier: Topic :: Utilities
Classifier: Topic :: Software Development :: Build Tools
Classifier: Framework :: AsyncIO
Classifier: Programming Language :: Python :: 3 :: Only
Classifier: Programming Language :: Python :: 3.5
Classifier: Intended Audience :: Developers
Classifier: Natural Language :: English
Classifier: License :: OSI Approved :: MIT License
Requires-Python: >=3.5
